[
  {
    "page": 1,
    "count": 3,
    "images": [
      {
        "index": 0,
        "width": 363,
        "height": 362
      },
      {
        "index": 1,
        "width": 360,
        "height": 363
      },
      {
        "index": 2,
        "width": 431,
        "height": 187
      }
    ]
  },
  {
    "page": 2,
    "count": 1,
    "images": [
      {
        "index": 0,
        "width": 1004,
        "height": 591
      }
    ]
  },
  {
    "page": 3,
    "count": 0,
    "images": []
  },
  {
    "page": 4,
    "count": 0,
    "images": []
  },
  {
    "page": 5,
    "count": 1,
    "images": [
      {
        "index": 0,
        "width": 1076,
        "height": 648
      }
    ]
  },
  {
    "page": 6,
    "count": 5,
    "images": [
      {
        "index": 0,
        "width": 1076,
        "height": 258
      },
      {
        "index": 1,
        "width": 365,
        "height": 366
      },
      {
        "index": 2,
        "width": 365,
        "height": 366
      },
      {
        "index": 3,
        "width": 365,
        "height": 365
      },
      {
        "index": 4,
        "width": 366,
        "height": 343
      }
    ]
  },
  {
    "page": 7,
    "count": 6,
    "images": [
      {
        "index": 0,
        "width": 365,
        "height": 360
      },
      {
        "index": 1,
        "width": 365,
        "height": 365
      },
      {
        "index": 2,
        "width": 365,
        "height": 366
      },
      {
        "index": 3,
        "width": 365,
        "height": 366
      },
      {
        "index": 4,
        "width": 366,
        "height": 344
      },
      {
        "index": 5,
        "width": 365,
        "height": 366
      }
    ]
  },
  {
    "page": 8,
    "count": 6,
    "images": [
      {
        "index": 0,
        "width": 365,
        "height": 360
      },
      {
        "index": 1,
        "width": 365,
        "height": 366
      },
      {
        "index": 2,
        "width": 365,
        "height": 365
      },
      {
        "index": 3,
        "width": 365,
        "height": 386
      },
      {
        "index": 4,
        "width": 365,
        "height": 366
      },
      {
        "index": 5,
        "width": 365,
        "height": 366
      }
    ]
  },
  {
    "page": 9,
    "count": 5,
    "images": [
      {
        "index": 0,
        "width": 365,
        "height": 365
      },
      {
        "index": 1,
        "width": 365,
        "height": 366
      },
      {
        "index": 2,
        "width": 365,
        "height": 366
      },
      {
        "index": 3,
        "width": 365,
        "height": 366
      },
      {
        "index": 4,
        "width": 365,
        "height": 366
      }
    ]
  }
]